tray_launcher/__init__.py
tray_launcher/child_script.py
tray_launcher/child_script_manager.py
tray_launcher/cli.py
tray_launcher/gui.py
tray_launcher/launcher_parser.py
tray_launcher/tray_launcher_client.py
tray_launcher/icons/check_mark.png
tray_launcher/icons/tray_icon.png
tray_launcher-1.0.9.dist-info/LICENSE
tray_launcher-1.0.9.dist-info/METADATA
tray_launcher-1.0.9.dist-info/WHEEL
tray_launcher-1.0.9.dist-info/entry_points.txt
tray_launcher-1.0.9.dist-info/top_level.txt
tray_launcher-1.0.9.dist-info/RECORD
