Metadata-Version: 2.1
Name: tray-launcher
Version: 1.0.9
Summary: A launcher for Windows that resides in the taskbar for managing .bat scripts.
Home-page: https://github.com/Jayich-Lab/tray-launcher/
Author: Huaxu Dan
Author-email: danhuaxutommy@gmail.com
Project-URL: Source Code, https://github.com/Jayich-Lab/tray-launcher/
Project-URL: Bug Tracker, https://github.com/Jayich-Lab/tray-launcher/issues/
Classifier: Development Status :: 4 - Beta
Classifier: Intended Audience :: Developers
Classifier: Intended Audience :: Science/Research
Classifier: License :: OSI Approved :: MIT License
Classifier: Natural Language :: English
Classifier: Operating System :: Microsoft :: Windows
Classifier: Programming Language :: Python :: 3 :: Only
Classifier: Topic :: System :: Logging
Classifier: Topic :: System :: Monitoring
Classifier: Topic :: Utilities
Requires-Python: ~=3.7
License-File: LICENSE
Requires-Dist: PyQt5
Requires-Dist: pywin32
Requires-Dist: psutil
